MANIFEST.in
README.txt
heddex.greenfield-configure.zcml
setup.cfg
setup.py
docs/HISTORY.txt
docs/INSTALL.txt
docs/LICENSE.GPL
docs/LICENSE.txt
heddex/__init__.py
heddex.greenfield.egg-info/PKG-INFO
heddex.greenfield.egg-info/SOURCES.txt
heddex.greenfield.egg-info/dependency_links.txt
heddex.greenfield.egg-info/entry_points.txt
heddex.greenfield.egg-info/namespace_packages.txt
heddex.greenfield.egg-info/not-zip-safe
heddex.greenfield.egg-info/paster_plugins.txt
heddex.greenfield.egg-info/requires.txt
heddex.greenfield.egg-info/top_level.txt
heddex/greenfield/__init__.py
heddex/greenfield/configure.zcml
heddex/greenfield/profiles.zcml
heddex/greenfield/setuphandlers.py
heddex/greenfield/skins.zcml
heddex/greenfield/tests.py
heddex/greenfield/version.txt
heddex/greenfield/browser/__init__.py
heddex/greenfield/browser/configure.zcml
heddex/greenfield/browser/interfaces.py
heddex/greenfield/browser/searchbox.pt
heddex/greenfield/browser/viewlets.py
heddex/greenfield/portlets/__init__.py
heddex/greenfield/portlets/configure.zcml
heddex/greenfield/portlets/greenfield_login.pt
heddex/greenfield/portlets/greenfield_search.pt
heddex/greenfield/portlets/navigation.pt
heddex/greenfield/profiles/default/cssregistry.xml
heddex/greenfield/profiles/default/heddex.greenfield_various.txt
heddex/greenfield/profiles/default/import_steps.xml
heddex/greenfield/profiles/default/metadata.xml
heddex/greenfield/profiles/default/skins.xml
heddex/greenfield/profiles/default/viewlets.xml
heddex/greenfield/skins/heddex_greenfield_custom_images/breadcrumbs-bullet.gif
heddex/greenfield/skins/heddex_greenfield_custom_images/breadcrumbs-bullet.gif.metadata
heddex/greenfield/skins/heddex_greenfield_custom_images/bullet.gif
heddex/greenfield/skins/heddex_greenfield_custom_images/bullet.gif.metadata
heddex/greenfield/skins/heddex_greenfield_custom_images/button-login-bg.gif
heddex/greenfield/skins/heddex_greenfield_custom_images/button-login-bg.gif.metadata
heddex/greenfield/skins/heddex_greenfield_custom_images/favicon.ico
heddex/greenfield/skins/heddex_greenfield_custom_images/footer-dotted-line.gif
heddex/greenfield/skins/heddex_greenfield_custom_images/footer-dotted-line.gif.metadata
heddex/greenfield/skins/heddex_greenfield_custom_images/globalnav-bg-hover.png
heddex/greenfield/skins/heddex_greenfield_custom_images/globalnav-bg-hover.png.metadata
