Metadata-Version: 1.0
Name: heddex.greenfield
Version: 2.0
Summary: An installable theme for Plone
Home-page: http://www.heddex.biz/
Author: Michael Krishtopa
Author-email: theo@heddex.biz
License: GPL
Keywords: heddex
Platform: UNKNOWN
Classifier: Framework :: Plone
Classifier: Programming Language :: Python
Classifier: Topic :: Software Development :: Libraries :: Python Modules
